ejpcsvparser/__init__.py
ejpcsvparser/csv_data.py
ejpcsvparser/parse.py
ejpcsvparser/settings.py
ejpcsvparser/utils.py
ejpcsvparser-0.5.0.dist-info/LICENSE
ejpcsvparser-0.5.0.dist-info/METADATA
ejpcsvparser-0.5.0.dist-info/WHEEL
ejpcsvparser-0.5.0.dist-info/top_level.txt
ejpcsvparser-0.5.0.dist-info/RECORD
