Metadata-Version: 2.1
Name: ejpcsvparser
Version: 0.5.0
Summary: EJP CSV parser for building article objects.
Home-page: https://github.com/elifesciences/ejp-csv-parser
Maintainer: eLife Sciences Publications Ltd.
Maintainer-email: tech-team@elifesciences.org
License: MIT
Classifier: Development Status :: 3 - Alpha
Classifier: Intended Audience :: Developers
Classifier: License :: OSI Approved :: MIT License
Classifier: Programming Language :: Python :: 3
Classifier: Programming Language :: Python :: 3.5
License-File: LICENSE
Requires-Dist: elifearticle >=0.20.0
Requires-Dist: elifetools >=0.46.0
Requires-Dist: GitPython
Requires-Dist: configparser
